db_utils/DBUtil.py
db_utils/__init__.py
db_utils/db_connect.py
db_utils/dynamodb_connect.py
db_utils/mysql_connect.py
db_utils/pg_connect.py
db_utils/s3_connect.py
db_utils/snowflake_connect.py
db_utils/sql_server_connect.py
db_utils/sqlite_connect.py
db_utils/timer.py
db_utils-0.4.6.dist-info/LICENSE
db_utils-0.4.6.dist-info/METADATA
db_utils-0.4.6.dist-info/WHEEL
db_utils-0.4.6.dist-info/top_level.txt
db_utils-0.4.6.dist-info/RECORD
