Metadata-Version: 2.1
Name: db-utils
Version: 0.4.6
Summary: Helper class to connect to Redshift, Snowflake, DynamoDB and S3
Home-page: https://github.com/ktechboston/db_utils
Author: Komodo Technologies, LLC
License: UNKNOWN
Platform: UNKNOWN
Classifier: Programming Language :: Python :: 3
Classifier: License :: OSI Approved :: MIT License
Classifier: Operating System :: OS Independent
Requires-Dist: boto3 (>=1.5.32)
Requires-Dist: psycopg2 (>=2.8.2)
Requires-Dist: psycopg2-binary (>=2.7.4numpy>=1.16.3)
Requires-Dist: pandas (==0.24.2)
Requires-Dist: sqlparse (>=0.2.4)
Requires-Dist: awscli (>=1.16.32)
Requires-Dist: snowflake-connector-python (>=1.7.3)
Requires-Dist: mysql-connector-python (>=8.0.15)
Requires-Dist: pyodbc (>=4.0.26)
Requires-Dist: jinja2 (>=2.10.1)
